{
  "kind": "collectionType",
  "collectionName": "categories",
  "info": {
    "name": "categorie"
  },
  "options": {
    "increments": true,
    "timestamps": true
  },
  "attributes": {
    "libelle": {
      "type": "string"
    },
    "icon": {
      "collection": "file",
      "via": "related",
      "allowedTypes": [
        "images",
        "files",
        "videos"
      ],
      "plugin": "upload",
      "required": false
    },
    "agences": {
      "via": "categorie",
      "collection": "agence"
    }
  }
}
